<?xml version='1.0' encoding='utf-8'?>
<annotation><folder>JPEGImages</folder><filename>0000103.jpg</filename><size><width>1920</width><height>1080</height><depth>3</depth></size><object><name>vehicle</name><bndbox><xmin>1115</xmin><ymin>532</ymin><xmax>1226</xmax><ymax>623</ymax></bndbox></object><object><name>vehicle</name><bndbox><xmin>961</xmin><ymin>533</ymin><xmax>1011</xmax><ymax>573</ymax></bndbox></object><object><name>vehicle</name><bndbox><xmin>626</xmin><ymin>583</ymin><xmax>704</xmax><ymax>683</ymax></bndbox></object></annotation>